ptorch_tools/__init__.py
ptorch_tools/loss.cp38-win_amd64.pyd
ptorch_tools/loss.py
ptorch_tools/metrics.cp38-win_amd64.pyd
ptorch_tools/metrics.py
ptorch_tools/model_components.cp38-win_amd64.pyd
ptorch_tools/model_components.py
ptorch_tools/utils.cp38-win_amd64.pyd
ptorch_tools/utils.py
ptorch_tools-0.2.2.dist-info/METADATA
ptorch_tools-0.2.2.dist-info/WHEEL
ptorch_tools-0.2.2.dist-info/top_level.txt
ptorch_tools-0.2.2.dist-info/zip-safe
ptorch_tools-0.2.2.dist-info/RECORD
