Metadata-Version: 2.1
Name: ptorch-tools
Version: 0.2.2
Summary: tools for ai torch
Home-page: https://pypi.org/ptorch_tools
Author: P
Author-email: abc@def.com
License: GPL Licence
Platform: UNKNOWN
Classifier: Operating System :: OS Independent
Classifier: Intended Audience :: Developers
Requires-Python: >=3.6, <3.10
Requires-Dist: tqdm
Requires-Dist: torch
Requires-Dist: numpy
Requires-Dist: pandas
